illiterate/__init__.py
illiterate/__main__.py
illiterate/cli.py
illiterate/config.py
illiterate/core.py
illiterate-0.5.0.dist-info/entry_points.txt
illiterate-0.5.0.dist-info/LICENSE
illiterate-0.5.0.dist-info/WHEEL
illiterate-0.5.0.dist-info/METADATA
illiterate-0.5.0.dist-info/RECORD
