Metadata-Version: 2.1
Name: illiterate
Version: 0.5.0
Summary: Unobtrusive literate programming experience for Python pragmatists
License: MIT
Author: Alejandro Piad
Author-email: alepiad@gmail.com
Requires-Python: >=3.8,<4.0
Classifier: License :: OSI Approved :: MIT License
Classifier: Programming Language :: Python :: 3
Classifier: Programming Language :: Python :: 3.10
Classifier: Programming Language :: Python :: 3.8
Classifier: Programming Language :: Python :: 3.9
Requires-Dist: PyYAML (==5.4.1)
Requires-Dist: pydantic (>=1.9.2,<2.0.0)
Requires-Dist: rich (>=9.0.1,<10.0.0)
Requires-Dist: typer (>=0.3.2,<0.4.0)
Requires-Dist: watchdog (>=2.1.9,<3.0.0)
